scenedetect/__init__.py
scenedetect/__main__.py
scenedetect/frame_timecode.py
scenedetect/platform.py
scenedetect/scene_detector.py
scenedetect/scene_manager.py
scenedetect/stats_manager.py
scenedetect/video_manager.py
scenedetect/video_splitter.py
scenedetect/video_stream.py
scenedetect/_cli/__init__.py
scenedetect/_cli/commands.py
scenedetect/_cli/config.py
scenedetect/_cli/context.py
scenedetect/_cli/controller.py
scenedetect/_thirdparty/__init__.py
scenedetect/_thirdparty/simpletable.py
scenedetect/backends/__init__.py
scenedetect/backends/moviepy.py
scenedetect/backends/opencv.py
scenedetect/backends/pyav.py
scenedetect/detectors/__init__.py
scenedetect/detectors/adaptive_detector.py
scenedetect/detectors/content_detector.py
scenedetect/detectors/hash_detector.py
scenedetect/detectors/histogram_detector.py
scenedetect/detectors/threshold_detector.py
scenedetect-0.6.7.dist-info/licenses/LICENSE
scenedetect-0.6.7.dist-info/METADATA
scenedetect-0.6.7.dist-info/WHEEL
scenedetect-0.6.7.dist-info/entry_points.txt
scenedetect-0.6.7.dist-info/top_level.txt
scenedetect-0.6.7.dist-info/RECORD
